{"name":"Login successful","id":"login-to-opencart;login-successful","testSteps":[{"number":1,"description":"Given Liseth open the page Opencart","duration":3737,"startTime":"2022-05-26T20:42:05.289-05:00[America/Bogota]","screenshots":[{"screenshot":"e1bf635de351e9b98cd48c26d2ea2185ee30684f4ed5f2152886f14165d4ee49.png","timeStamp":1653615729026}],"result":"SUCCESS","precondition":false,"level":0,"children":[{"number":2,"description":"Liseth open up","duration":3544,"startTime":"2022-05-26T20:42:05.471-05:00[America/Bogota]","screenshots":[{"screenshot":"e1bf635de351e9b98cd48c26d2ea2185ee30684f4ed5f2152886f14165d4ee49.png","timeStamp":1653615729015}],"result":"SUCCESS","precondition":false,"level":1,"children":[{"number":3,"description":"Liseth opens the Opencart page","duration":3504,"startTime":"2022-05-26T20:42:05.485-05:00[America/Bogota]","screenshots":[{"screenshot":"e1bf635de351e9b98cd48c26d2ea2185ee30684f4ed5f2152886f14165d4ee49.png","timeStamp":1653615728989}],"result":"SUCCESS","precondition":false,"level":2}]}]},{"number":4,"description":"When she log in with the credentials\r\n| username | password |\r\n| demo | demo |","duration":2064,"startTime":"2022-05-26T20:42:09.026-05:00[America/Bogota]","screenshots":[{"screenshot":"92214d606389bddc2a5fd9253428773e0439bc82c6b468fd33b3c707b7424466.png","timeStamp":1653615731090}],"result":"SUCCESS","precondition":false,"level":0,"children":[{"number":5,"description":"Liseth login opencart","duration":2044,"startTime":"2022-05-26T20:42:09.036-05:00[America/Bogota]","screenshots":[{"screenshot":"92214d606389bddc2a5fd9253428773e0439bc82c6b468fd33b3c707b7424466.png","timeStamp":1653615731079}],"result":"SUCCESS","precondition":false,"level":1,"children":[{"number":6,"description":"Liseth clears field where do we write the user","duration":146,"startTime":"2022-05-26T20:42:09.061-05:00[America/Bogota]","screenshots":[{"screenshot":"a42a860cbb66dc13480c311e7020c58155bc8fd187dd704fd70c9d7e7c1238bf.png","timeStamp":1653615729207}],"result":"SUCCESS","precondition":false,"level":2},{"number":7,"description":"Liseth enters \u0027demo\u0027 into where do we write the user","duration":291,"startTime":"2022-05-26T20:42:09.208-05:00[America/Bogota]","screenshots":[{"screenshot":"b0cdfda6a7af344a142eb89b7e0a71a3c286e6fbd745c976abe70f115d459325.png","timeStamp":1653615729499}],"result":"SUCCESS","precondition":false,"level":2},{"number":8,"description":"Liseth clears field where do we write the password","duration":48,"startTime":"2022-05-26T20:42:09.500-05:00[America/Bogota]","screenshots":[{"screenshot":"b0cdfda6a7af344a142eb89b7e0a71a3c286e6fbd745c976abe70f115d459325.png","timeStamp":1653615729548}],"result":"SUCCESS","precondition":false,"level":2},{"number":9,"description":"Liseth enters \u0027demo\u0027 into where do we write the password","duration":217,"startTime":"2022-05-26T20:42:09.549-05:00[America/Bogota]","screenshots":[{"screenshot":"4816a0ba15b5f2ff999edb6eb7ae34365a96d87ef4be361875996a72e6b30c47.png","timeStamp":1653615729765}],"result":"SUCCESS","precondition":false,"level":2},{"number":10,"description":"Liseth clicks on button to confirm login","duration":1301,"startTime":"2022-05-26T20:42:09.767-05:00[America/Bogota]","screenshots":[{"screenshot":"92214d606389bddc2a5fd9253428773e0439bc82c6b468fd33b3c707b7424466.png","timeStamp":1653615731068}],"result":"SUCCESS","precondition":false,"level":2}]}]},{"number":11,"description":"Then she can browse the page","duration":227,"startTime":"2022-05-26T20:42:11.090-05:00[America/Bogota]","screenshots":[{"screenshot":"92214d606389bddc2a5fd9253428773e0439bc82c6b468fd33b3c707b7424466.png","timeStamp":1653615731317}],"result":"SUCCESS","precondition":false,"level":0,"children":[{"number":12,"description":"Then home page","duration":162,"startTime":"2022-05-26T20:42:11.144-05:00[America/Bogota]","screenshots":[{"screenshot":"92214d606389bddc2a5fd9253428773e0439bc82c6b468fd33b3c707b7424466.png","timeStamp":1653615731306}],"result":"SUCCESS","precondition":false,"level":1}]}],"userStory":{"id":"login-to-opencart","storyName":"Login to Opencart","displayName":"Login to Opencart","path":"Login.feature","narrative":"  As an Opencart client\n  I want to start session\n  To browse the web page","type":"feature"},"featureTag":{"name":"Login to Opencart","type":"feature","displayName":"Login to Opencart"},"title":"Login successful","description":"","tags":[{"name":"LoginSuccessful","type":"tag","displayName":"LoginSuccessful"},{"name":"Login to Opencart","type":"feature","displayName":"Login to Opencart"}],"startTime":"2022-05-26T20:42:05.181-05:00[America/Bogota]","duration":6138,"projectKey":"","sessionId":"5912bce09ac0d62d6ad0e2a2f86e3c79","driver":"chrome:liseth","isManualTestingUpToDate":false,"manual":false,"testSource":"Cucumber","actors":[{"name":"Liseth","can":["browse the web"]}],"result":"SUCCESS"}